{
  "combo": "IF+hours_since_start+log1p_amount+A_top2",
  "cv_method": "purgedcv.WalkForwardSplit",
  "tune_n_splits": 5,
  "tune_selection": "AUC-PR primary, logloss tie-break (all stages)",
  "ES_FRAC": 0.2,
  "MODEL_FEATURES": [
    "V1",
    "V2",
    "V3",
    "V4",
    "V5",
    "V6",
    "V7",
    "V8",
    "V9",
    "V10",
    "V11",
    "V12",
    "V13",
    "V14",
    "V15",
    "V16",
    "V17",
    "V18",
    "V19",
    "V20",
    "V21",
    "V22",
    "V23",
    "V24",
    "V25",
    "V26",
    "V27",
    "V28",
    "Amount",
    "Time",
    "if_oof_score",
    "hours_since_start",
    "log1p_amount",
    "one_euro_V14",
    "one_euro_V4"
  ],
  "best_model": "XGBoost",
  "best_params": {
    "learning_rate": 0.07,
    "weight_scheme": "spw_sqrt",
    "max_depth": 6,
    "min_child_weight": 1,
    "subsample": 0.6,
    "colsample_bytree": 0.6,
    "reg_alpha": 0.1,
    "reg_lambda": 0.01
  },
  "best_lgb_params": {
    "learning_rate": 0.05,
    "weight_scheme": "spw_2x",
    "max_depth": 3,
    "num_leaves": 15,
    "min_child_samples": 40,
    "subsample": 0.6,
    "colsample_bytree": 0.8,
    "reg_alpha": 0.1,
    "reg_lambda": 0.1
  },
  "best_xgb_params": {
    "learning_rate": 0.07,
    "weight_scheme": "spw_sqrt",
    "max_depth": 6,
    "min_child_weight": 1,
    "subsample": 0.6,
    "colsample_bytree": 0.6,
    "reg_alpha": 0.1,
    "reg_lambda": 0.01
  },
  "final_metrics": {
    "model": "XGBoost",
    "cv_method": "purgedcv.WalkForwardSplit",
    "AUC-PR": 0.7981549859643631,
    "best_threshold": 0.48,
    "F1": 0.6716981132075471,
    "Precision": 0.8811881188118812,
    "Recall": 0.5426829268292683,
    "FP": 36,
    "FN": 225
  },
  "final_cv": {
    "LightGBM": {
      "model": "LightGBM",
      "logloss_mean": 0.0038253802052318673,
      "logloss_std": 0.0009693735293941762,
      "AUC-PR_mean": 0.7961023786867394,
      "AUC-PR_std": 0.026922440461467516,
      "F1": 0.6674846625766871,
      "Precision": 0.8421052631578947,
      "Recall": 0.5528455284552846,
      "FP": 51,
      "FN": 220
    },
    "XGBoost": {
      "model": "XGBoost",
      "logloss_mean": 0.002972006911405177,
      "logloss_std": 0.0005452146075976913,
      "AUC-PR_mean": 0.7981549859643631,
      "AUC-PR_std": 0.030253671687327992,
      "F1": 0.6716981132075471,
      "Precision": 0.8811881188118812,
      "Recall": 0.5426829268292683,
      "FP": 36,
      "FN": 225
    }
  }
}